unscramble/__init__.py
unscramble/unscramble.py
unscramble/data/words_alpha.txt
Unscramble-0.2.dist-info/METADATA
Unscramble-0.2.dist-info/WHEEL
Unscramble-0.2.dist-info/top_level.txt
Unscramble-0.2.dist-info/RECORD
