Metadata-Version: 2.1
Name: Unscramble
Version: 0.2
Summary: Unscramble a word
Home-page: https://github.com/arpit625/unscramble
Author: Arpit Gupta
Author-email: arpit.gupta@ucdconnect.ie
License: MIT
Platform: UNKNOWN
Classifier: Programming Language :: Python :: 3
Classifier: License :: OSI Approved :: MIT License
Classifier: Operating System :: OS Independent
Requires-Dist: tqdm
